{"nodes": [{"id": "c_wamp27_www_travel_opps_backend_app_http_controllers_menucontroller_php", "label": "MenuController.php", "file_type": "code", "source_file": "C:\\wamp27\\www\\travel_opps\\backend\\app\\Http\\Controllers\\MenuController.php", "source_location": "L1"}, {"id": "menucontroller_menucontroller", "label": "MenuController", "file_type": "code", "source_file": "C:\\wamp27\\www\\travel_opps\\backend\\app\\Http\\Controllers\\MenuController.php", "source_location": "L10"}, {"id": "menucontroller_menucontroller_getdefaultmenu", "label": ".getDefaultMenu()", "file_type": "code", "source_file": "C:\\wamp27\\www\\travel_opps\\backend\\app\\Http\\Controllers\\MenuController.php", "source_location": "L16"}, {"id": "menucontroller_menucontroller_index", "label": ".index()", "file_type": "code", "source_file": "C:\\wamp27\\www\\travel_opps\\backend\\app\\Http\\Controllers\\MenuController.php", "source_location": "L114"}, {"id": "menucontroller_menucontroller_update", "label": ".update()", "file_type": "code", "source_file": "C:\\wamp27\\www\\travel_opps\\backend\\app\\Http\\Controllers\\MenuController.php", "source_location": "L145"}], "edges": [{"source": "c_wamp27_www_travel_opps_backend_app_http_controllers_menucontroller_php", "target": "setting", "relation": "imports", "confidence": "EXTRACTED", "source_file": "C:\\wamp27\\www\\travel_opps\\backend\\app\\Http\\Controllers\\MenuController.php", "source_location": "L5", "weight": 1.0}, {"source": "c_wamp27_www_travel_opps_backend_app_http_controllers_menucontroller_php", "target": "jsonresponse", "relation": "imports", "confidence": "EXTRACTED", "source_file": "C:\\wamp27\\www\\travel_opps\\backend\\app\\Http\\Controllers\\MenuController.php", "source_location": "L6", "weight": 1.0}, {"source": "c_wamp27_www_travel_opps_backend_app_http_controllers_menucontroller_php", "target": "request", "relation": "imports", "confidence": "EXTRACTED", "source_file": "C:\\wamp27\\www\\travel_opps\\backend\\app\\Http\\Controllers\\MenuController.php", "source_location": "L7", "weight": 1.0}, {"source": "c_wamp27_www_travel_opps_backend_app_http_controllers_menucontroller_php", "target": "auth", "relation": "imports", "confidence": "EXTRACTED", "source_file": "C:\\wamp27\\www\\travel_opps\\backend\\app\\Http\\Controllers\\MenuController.php", "source_location": "L8", "weight": 1.0}, {"source": "c_wamp27_www_travel_opps_backend_app_http_controllers_menucontroller_php", "target": "menucontroller_menucontroller", "relation": "contains", "confidence": "EXTRACTED", "source_file": "C:\\wamp27\\www\\travel_opps\\backend\\app\\Http\\Controllers\\MenuController.php", "source_location": "L10", "weight": 1.0}, {"source": "menucontroller_menucontroller", "target": "menucontroller_menucontroller_getdefaultmenu", "relation": "method", "confidence": "EXTRACTED", "source_file": "C:\\wamp27\\www\\travel_opps\\backend\\app\\Http\\Controllers\\MenuController.php", "source_location": "L16", "weight": 1.0}, {"source": "menucontroller_menucontroller", "target": "menucontroller_menucontroller_index", "relation": "method", "confidence": "EXTRACTED", "source_file": "C:\\wamp27\\www\\travel_opps\\backend\\app\\Http\\Controllers\\MenuController.php", "source_location": "L114", "weight": 1.0}, {"source": "menucontroller_menucontroller", "target": "menucontroller_menucontroller_update", "relation": "method", "confidence": "EXTRACTED", "source_file": "C:\\wamp27\\www\\travel_opps\\backend\\app\\Http\\Controllers\\MenuController.php", "source_location": "L145", "weight": 1.0}, {"source": "menucontroller_menucontroller_index", "target": "menucontroller_menucontroller", "relation": "calls", "confidence": "EXTRACTED", "source_file": "C:\\wamp27\\www\\travel_opps\\backend\\app\\Http\\Controllers\\MenuController.php", "source_location": "L125", "weight": 1.0}], "raw_calls": [{"caller_nid": "menucontroller_menucontroller_index", "callee": "Auth", "source_file": "C:\\wamp27\\www\\travel_opps\\backend\\app\\Http\\Controllers\\MenuController.php", "source_location": "L117"}, {"caller_nid": "menucontroller_menucontroller_index", "callee": "Auth", "source_file": "C:\\wamp27\\www\\travel_opps\\backend\\app\\Http\\Controllers\\MenuController.php", "source_location": "L117"}, {"caller_nid": "menucontroller_menucontroller_index", "callee": "\\Illuminate\\Support\\Facades\\Cache", "source_file": "C:\\wamp27\\www\\travel_opps\\backend\\app\\Http\\Controllers\\MenuController.php", "source_location": "L121"}, {"caller_nid": "menucontroller_menucontroller_index", "callee": "addHours", "source_file": "C:\\wamp27\\www\\travel_opps\\backend\\app\\Http\\Controllers\\MenuController.php", "source_location": "L121"}, {"caller_nid": "menucontroller_menucontroller_index", "callee": "now", "source_file": "C:\\wamp27\\www\\travel_opps\\backend\\app\\Http\\Controllers\\MenuController.php", "source_location": "L121"}, {"caller_nid": "menucontroller_menucontroller_index", "callee": "first", "source_file": "C:\\wamp27\\www\\travel_opps\\backend\\app\\Http\\Controllers\\MenuController.php", "source_location": "L122"}, {"caller_nid": "menucontroller_menucontroller_index", "callee": "Setting", "source_file": "C:\\wamp27\\www\\travel_opps\\backend\\app\\Http\\Controllers\\MenuController.php", "source_location": "L122"}, {"caller_nid": "menucontroller_menucontroller_index", "callee": "empty", "source_file": "C:\\wamp27\\www\\travel_opps\\backend\\app\\Http\\Controllers\\MenuController.php", "source_location": "L123"}, {"caller_nid": "menucontroller_menucontroller_index", "callee": "json_decode", "source_file": "C:\\wamp27\\www\\travel_opps\\backend\\app\\Http\\Controllers\\MenuController.php", "source_location": "L124"}, {"caller_nid": "menucontroller_menucontroller_index", "callee": "is_array", "source_file": "C:\\wamp27\\www\\travel_opps\\backend\\app\\Http\\Controllers\\MenuController.php", "source_location": "L127"}, {"caller_nid": "menucontroller_menucontroller_index", "callee": "json", "source_file": "C:\\wamp27\\www\\travel_opps\\backend\\app\\Http\\Controllers\\MenuController.php", "source_location": "L130"}, {"caller_nid": "menucontroller_menucontroller_index", "callee": "response", "source_file": "C:\\wamp27\\www\\travel_opps\\backend\\app\\Http\\Controllers\\MenuController.php", "source_location": "L130"}, {"caller_nid": "menucontroller_menucontroller_index", "callee": "json", "source_file": "C:\\wamp27\\www\\travel_opps\\backend\\app\\Http\\Controllers\\MenuController.php", "source_location": "L135"}, {"caller_nid": "menucontroller_menucontroller_index", "callee": "response", "source_file": "C:\\wamp27\\www\\travel_opps\\backend\\app\\Http\\Controllers\\MenuController.php", "source_location": "L135"}, {"caller_nid": "menucontroller_menucontroller_update", "callee": "validate", "source_file": "C:\\wamp27\\www\\travel_opps\\backend\\app\\Http\\Controllers\\MenuController.php", "source_location": "L148"}, {"caller_nid": "menucontroller_menucontroller_update", "callee": "input", "source_file": "C:\\wamp27\\www\\travel_opps\\backend\\app\\Http\\Controllers\\MenuController.php", "source_location": "L152"}, {"caller_nid": "menucontroller_menucontroller_update", "callee": "Auth", "source_file": "C:\\wamp27\\www\\travel_opps\\backend\\app\\Http\\Controllers\\MenuController.php", "source_location": "L153"}, {"caller_nid": "menucontroller_menucontroller_update", "callee": "Auth", "source_file": "C:\\wamp27\\www\\travel_opps\\backend\\app\\Http\\Controllers\\MenuController.php", "source_location": "L153"}, {"caller_nid": "menucontroller_menucontroller_update", "callee": "\\Illuminate\\Support\\Facades\\Cache", "source_file": "C:\\wamp27\\www\\travel_opps\\backend\\app\\Http\\Controllers\\MenuController.php", "source_location": "L157"}, {"caller_nid": "menucontroller_menucontroller_update", "callee": "Setting", "source_file": "C:\\wamp27\\www\\travel_opps\\backend\\app\\Http\\Controllers\\MenuController.php", "source_location": "L159"}, {"caller_nid": "menucontroller_menucontroller_update", "callee": "json_encode", "source_file": "C:\\wamp27\\www\\travel_opps\\backend\\app\\Http\\Controllers\\MenuController.php", "source_location": "L162"}, {"caller_nid": "menucontroller_menucontroller_update", "callee": "json", "source_file": "C:\\wamp27\\www\\travel_opps\\backend\\app\\Http\\Controllers\\MenuController.php", "source_location": "L168"}, {"caller_nid": "menucontroller_menucontroller_update", "callee": "response", "source_file": "C:\\wamp27\\www\\travel_opps\\backend\\app\\Http\\Controllers\\MenuController.php", "source_location": "L168"}, {"caller_nid": "menucontroller_menucontroller_update", "callee": "json", "source_file": "C:\\wamp27\\www\\travel_opps\\backend\\app\\Http\\Controllers\\MenuController.php", "source_location": "L174"}, {"caller_nid": "menucontroller_menucontroller_update", "callee": "response", "source_file": "C:\\wamp27\\www\\travel_opps\\backend\\app\\Http\\Controllers\\MenuController.php", "source_location": "L174"}, {"caller_nid": "menucontroller_menucontroller_update", "callee": "config", "source_file": "C:\\wamp27\\www\\travel_opps\\backend\\app\\Http\\Controllers\\MenuController.php", "source_location": "L177"}, {"caller_nid": "menucontroller_menucontroller_update", "callee": "getMessage", "source_file": "C:\\wamp27\\www\\travel_opps\\backend\\app\\Http\\Controllers\\MenuController.php", "source_location": "L177"}]}