{"nodes": [{"id": "c_wamp27_www_travel_opps_frontend_src_components_dashboard_dashboardstatscards_jsx", "label": "DashboardStatsCards.jsx", "file_type": "code", "source_file": "C:\\wamp27\\www\\travel_opps\\frontend\\src\\components\\dashboard\\DashboardStatsCards.jsx", "source_location": "L1"}, {"id": "dashboardstatscards_dashboardstatscards", "label": "DashboardStatsCards()", "file_type": "code", "source_file": "C:\\wamp27\\www\\travel_opps\\frontend\\src\\components\\dashboard\\DashboardStatsCards.jsx", "source_location": "L30"}], "edges": [{"source": "c_wamp27_www_travel_opps_frontend_src_components_dashboard_dashboardstatscards_jsx", "target": "react", "relation": "imports_from", "confidence": "EXTRACTED", "source_file": "C:\\wamp27\\www\\travel_opps\\frontend\\src\\components\\dashboard\\DashboardStatsCards.jsx", "source_location": "L1", "weight": 1.0}, {"source": "c_wamp27_www_travel_opps_frontend_src_components_dashboard_dashboardstatscards_jsx", "target": "react_router_dom", "relation": "imports_from", "confidence": "EXTRACTED", "source_file": "C:\\wamp27\\www\\travel_opps\\frontend\\src\\components\\dashboard\\DashboardStatsCards.jsx", "source_location": "L2", "weight": 1.0}, {"source": "c_wamp27_www_travel_opps_frontend_src_components_dashboard_dashboardstatscards_jsx", "target": "lucide_react", "relation": "imports_from", "confidence": "EXTRACTED", "source_file": "C:\\wamp27\\www\\travel_opps\\frontend\\src\\components\\dashboard\\DashboardStatsCards.jsx", "source_location": "L3", "weight": 1.0}, {"source": "c_wamp27_www_travel_opps_frontend_src_components_dashboard_dashboardstatscards_jsx", "target": "dashboardstatscards_dashboardstatscards", "relation": "contains", "confidence": "EXTRACTED", "source_file": "C:\\wamp27\\www\\travel_opps\\frontend\\src\\components\\dashboard\\DashboardStatsCards.jsx", "source_location": "L30", "weight": 1.0}], "raw_calls": [{"caller_nid": "dashboardstatscards_dashboardstatscards", "callee": "map", "source_file": "C:\\wamp27\\www\\travel_opps\\frontend\\src\\components\\dashboard\\DashboardStatsCards.jsx", "source_location": "L33"}]}