{"nodes": [{"id": "c_wamp27_www_travel_opps_mycrmapp_ios_mycrmapp_main_m", "label": "main.m", "file_type": "code", "source_file": "C:\\wamp27\\www\\travel_opps\\MyCRMApp\\ios\\MyCRMApp\\main.m", "source_location": "L1"}], "edges": [{"source": "c_wamp27_www_travel_opps_mycrmapp_ios_mycrmapp_main_m", "target": "uikit", "relation": "imports", "confidence": "EXTRACTED", "source_file": "C:\\wamp27\\www\\travel_opps\\MyCRMApp\\ios\\MyCRMApp\\main.m", "source_location": "L1", "weight": 1.0}, {"source": "c_wamp27_www_travel_opps_mycrmapp_ios_mycrmapp_main_m", "target": "appdelegate", "relation": "imports", "confidence": "EXTRACTED", "source_file": "C:\\wamp27\\www\\travel_opps\\MyCRMApp\\ios\\MyCRMApp\\main.m", "source_location": "L3", "weight": 1.0}], "input_tokens": 0, "output_tokens": 0}