{"nodes": [{"id": "c_wamp27_www_travel_opps_backend_app_http_controllers_hotelcontroller_php", "label": "HotelController.php", "file_type": "code", "source_file": "C:\\wamp27\\www\\travel_opps\\backend\\app\\Http\\Controllers\\HotelController.php", "source_location": "L1"}, {"id": "hotelcontroller_hotelcontroller", "label": "HotelController", "file_type": "code", "source_file": "C:\\wamp27\\www\\travel_opps\\backend\\app\\Http\\Controllers\\HotelController.php", "source_location": "L13"}, {"id": "hotelcontroller_hotelcontroller_construct", "label": ".__construct()", "file_type": "code", "source_file": "C:\\wamp27\\www\\travel_opps\\backend\\app\\Http\\Controllers\\HotelController.php", "source_location": "L19"}, {"id": "hotelcontroller_hotelcontroller_getmodel", "label": ".getModel()", "file_type": "code", "source_file": "C:\\wamp27\\www\\travel_opps\\backend\\app\\Http\\Controllers\\HotelController.php", "source_location": "L24"}, {"id": "hotelcontroller_hotelcontroller_getvalidationrules", "label": ".getValidationRules()", "file_type": "code", "source_file": "C:\\wamp27\\www\\travel_opps\\backend\\app\\Http\\Controllers\\HotelController.php", "source_location": "L29"}, {"id": "hotelcontroller_hotelcontroller_formatresource", "label": ".formatResource()", "file_type": "code", "source_file": "C:\\wamp27\\www\\travel_opps\\backend\\app\\Http\\Controllers\\HotelController.php", "source_location": "L43"}, {"id": "hotelcontroller_hotelcontroller_store", "label": ".store()", "file_type": "code", "source_file": "C:\\wamp27\\www\\travel_opps\\backend\\app\\Http\\Controllers\\HotelController.php", "source_location": "L69"}, {"id": "hotelcontroller_hotelcontroller_update", "label": ".update()", "file_type": "code", "source_file": "C:\\wamp27\\www\\travel_opps\\backend\\app\\Http\\Controllers\\HotelController.php", "source_location": "L105"}, {"id": "hotelcontroller_hotelcontroller_destroy", "label": ".destroy()", "file_type": "code", "source_file": "C:\\wamp27\\www\\travel_opps\\backend\\app\\Http\\Controllers\\HotelController.php", "source_location": "L150"}, {"id": "hotelcontroller_hotelcontroller_search", "label": ".search()", "file_type": "code", "source_file": "C:\\wamp27\\www\\travel_opps\\backend\\app\\Http\\Controllers\\HotelController.php", "source_location": "L168"}, {"id": "hotelcontroller_hotelcontroller_export", "label": ".export()", "file_type": "code", "source_file": "C:\\wamp27\\www\\travel_opps\\backend\\app\\Http\\Controllers\\HotelController.php", "source_location": "L189"}], "edges": [{"source": "c_wamp27_www_travel_opps_backend_app_http_controllers_hotelcontroller_php", "target": "hotel", "relation": "imports", "confidence": "EXTRACTED", "source_file": "C:\\wamp27\\www\\travel_opps\\backend\\app\\Http\\Controllers\\HotelController.php", "source_location": "L5", "weight": 1.0}, {"source": "c_wamp27_www_travel_opps_backend_app_http_controllers_hotelcontroller_php", "target": "fileuploadservice", "relation": "imports", "confidence": "EXTRACTED", "source_file": "C:\\wamp27\\www\\travel_opps\\backend\\app\\Http\\Controllers\\HotelController.php", "source_location": "L6", "weight": 1.0}, {"source": "c_wamp27_www_travel_opps_backend_app_http_controllers_hotelcontroller_php", "target": "genericcrudtrait", "relation": "imports", "confidence": "EXTRACTED", "source_file": "C:\\wamp27\\www\\travel_opps\\backend\\app\\Http\\Controllers\\HotelController.php", "source_location": "L7", "weight": 1.0}, {"source": "c_wamp27_www_travel_opps_backend_app_http_controllers_hotelcontroller_php", "target": "jsonresponse", "relation": "imports", "confidence": "EXTRACTED", "source_file": "C:\\wamp27\\www\\travel_opps\\backend\\app\\Http\\Controllers\\HotelController.php", "source_location": "L8", "weight": 1.0}, {"source": "c_wamp27_www_travel_opps_backend_app_http_controllers_hotelcontroller_php", "target": "request", "relation": "imports", "confidence": "EXTRACTED", "source_file": "C:\\wamp27\\www\\travel_opps\\backend\\app\\Http\\Controllers\\HotelController.php", "source_location": "L9", "weight": 1.0}, {"source": "c_wamp27_www_travel_opps_backend_app_http_controllers_hotelcontroller_php", "target": "validator", "relation": "imports", "confidence": "EXTRACTED", "source_file": "C:\\wamp27\\www\\travel_opps\\backend\\app\\Http\\Controllers\\HotelController.php", "source_location": "L10", "weight": 1.0}, {"source": "c_wamp27_www_travel_opps_backend_app_http_controllers_hotelcontroller_php", "target": "streamedresponse", "relation": "imports", "confidence": "EXTRACTED", "source_file": "C:\\wamp27\\www\\travel_opps\\backend\\app\\Http\\Controllers\\HotelController.php", "source_location": "L11", "weight": 1.0}, {"source": "c_wamp27_www_travel_opps_backend_app_http_controllers_hotelcontroller_php", "target": "hotelcontroller_hotelcontroller", "relation": "contains", "confidence": "EXTRACTED", "source_file": "C:\\wamp27\\www\\travel_opps\\backend\\app\\Http\\Controllers\\HotelController.php", "source_location": "L13", "weight": 1.0}, {"source": "hotelcontroller_hotelcontroller", "target": "hotelcontroller_hotelcontroller_construct", "relation": "method", "confidence": "EXTRACTED", "source_file": "C:\\wamp27\\www\\travel_opps\\backend\\app\\Http\\Controllers\\HotelController.php", "source_location": "L19", "weight": 1.0}, {"source": "hotelcontroller_hotelcontroller", "target": "hotelcontroller_hotelcontroller_getmodel", "relation": "method", "confidence": "EXTRACTED", "source_file": "C:\\wamp27\\www\\travel_opps\\backend\\app\\Http\\Controllers\\HotelController.php", "source_location": "L24", "weight": 1.0}, {"source": "hotelcontroller_hotelcontroller", "target": "hotelcontroller_hotelcontroller_getvalidationrules", "relation": "method", "confidence": "EXTRACTED", "source_file": "C:\\wamp27\\www\\travel_opps\\backend\\app\\Http\\Controllers\\HotelController.php", "source_location": "L29", "weight": 1.0}, {"source": "hotelcontroller_hotelcontroller", "target": "hotelcontroller_hotelcontroller_formatresource", "relation": "method", "confidence": "EXTRACTED", "source_file": "C:\\wamp27\\www\\travel_opps\\backend\\app\\Http\\Controllers\\HotelController.php", "source_location": "L43", "weight": 1.0}, {"source": "hotelcontroller_hotelcontroller", "target": "hotelcontroller_hotelcontroller_store", "relation": "method", "confidence": "EXTRACTED", "source_file": "C:\\wamp27\\www\\travel_opps\\backend\\app\\Http\\Controllers\\HotelController.php", "source_location": "L69", "weight": 1.0}, {"source": "hotelcontroller_hotelcontroller", "target": "hotelcontroller_hotelcontroller_update", "relation": "method", "confidence": "EXTRACTED", "source_file": "C:\\wamp27\\www\\travel_opps\\backend\\app\\Http\\Controllers\\HotelController.php", "source_location": "L105", "weight": 1.0}, {"source": "hotelcontroller_hotelcontroller", "target": "hotelcontroller_hotelcontroller_destroy", "relation": "method", "confidence": "EXTRACTED", "source_file": "C:\\wamp27\\www\\travel_opps\\backend\\app\\Http\\Controllers\\HotelController.php", "source_location": "L150", "weight": 1.0}, {"source": "hotelcontroller_hotelcontroller", "target": "hotelcontroller_hotelcontroller_search", "relation": "method", "confidence": "EXTRACTED", "source_file": "C:\\wamp27\\www\\travel_opps\\backend\\app\\Http\\Controllers\\HotelController.php", "source_location": "L168", "weight": 1.0}, {"source": "hotelcontroller_hotelcontroller", "target": "hotelcontroller_hotelcontroller_export", "relation": "method", "confidence": "EXTRACTED", "source_file": "C:\\wamp27\\www\\travel_opps\\backend\\app\\Http\\Controllers\\HotelController.php", "source_location": "L189", "weight": 1.0}, {"source": "hotelcontroller_hotelcontroller_store", "target": "hotelcontroller_hotelcontroller_getvalidationrules", "relation": "calls", "confidence": "EXTRACTED", "source_file": "C:\\wamp27\\www\\travel_opps\\backend\\app\\Http\\Controllers\\HotelController.php", "source_location": "L72", "weight": 1.0}, {"source": "hotelcontroller_hotelcontroller_store", "target": "hotelcontroller_hotelcontroller_formatresource", "relation": "calls", "confidence": "EXTRACTED", "source_file": "C:\\wamp27\\www\\travel_opps\\backend\\app\\Http\\Controllers\\HotelController.php", "source_location": "L96", "weight": 1.0}, {"source": "hotelcontroller_hotelcontroller_update", "target": "hotelcontroller_hotelcontroller_formatresource", "relation": "calls", "confidence": "EXTRACTED", "source_file": "C:\\wamp27\\www\\travel_opps\\backend\\app\\Http\\Controllers\\HotelController.php", "source_location": "L141", "weight": 1.0}, {"source": "hotelcontroller_hotelcontroller_search", "target": "hotelcontroller_hotelcontroller_formatresource", "relation": "calls", "confidence": "EXTRACTED", "source_file": "C:\\wamp27\\www\\travel_opps\\backend\\app\\Http\\Controllers\\HotelController.php", "source_location": "L178", "weight": 1.0}], "raw_calls": [{"caller_nid": "hotelcontroller_hotelcontroller_formatresource", "callee": "asset", "source_file": "C:\\wamp27\\www\\travel_opps\\backend\\app\\Http\\Controllers\\HotelController.php", "source_location": "L51"}, {"caller_nid": "hotelcontroller_hotelcontroller_store", "callee": "Validator", "source_file": "C:\\wamp27\\www\\travel_opps\\backend\\app\\Http\\Controllers\\HotelController.php", "source_location": "L72"}, {"caller_nid": "hotelcontroller_hotelcontroller_store", "callee": "all", "source_file": "C:\\wamp27\\www\\travel_opps\\backend\\app\\Http\\Controllers\\HotelController.php", "source_location": "L72"}, {"caller_nid": "hotelcontroller_hotelcontroller_store", "callee": "fails", "source_file": "C:\\wamp27\\www\\travel_opps\\backend\\app\\Http\\Controllers\\HotelController.php", "source_location": "L73"}, {"caller_nid": "hotelcontroller_hotelcontroller_store", "callee": "validationErrorResponse", "source_file": "C:\\wamp27\\www\\travel_opps\\backend\\app\\Http\\Controllers\\HotelController.php", "source_location": "L74"}, {"caller_nid": "hotelcontroller_hotelcontroller_store", "callee": "hasFile", "source_file": "C:\\wamp27\\www\\travel_opps\\backend\\app\\Http\\Controllers\\HotelController.php", "source_location": "L76"}, {"caller_nid": "hotelcontroller_hotelcontroller_store", "callee": "upload", "source_file": "C:\\wamp27\\www\\travel_opps\\backend\\app\\Http\\Controllers\\HotelController.php", "source_location": "L77"}, {"caller_nid": "hotelcontroller_hotelcontroller_store", "callee": "file", "source_file": "C:\\wamp27\\www\\travel_opps\\backend\\app\\Http\\Controllers\\HotelController.php", "source_location": "L77"}, {"caller_nid": "hotelcontroller_hotelcontroller_store", "callee": "Hotel", "source_file": "C:\\wamp27\\www\\travel_opps\\backend\\app\\Http\\Controllers\\HotelController.php", "source_location": "L80"}, {"caller_nid": "hotelcontroller_hotelcontroller_store", "callee": "array_merge", "source_file": "C:\\wamp27\\www\\travel_opps\\backend\\app\\Http\\Controllers\\HotelController.php", "source_location": "L80"}, {"caller_nid": "hotelcontroller_hotelcontroller_store", "callee": "only", "source_file": "C:\\wamp27\\www\\travel_opps\\backend\\app\\Http\\Controllers\\HotelController.php", "source_location": "L80"}, {"caller_nid": "hotelcontroller_hotelcontroller_store", "callee": "id", "source_file": "C:\\wamp27\\www\\travel_opps\\backend\\app\\Http\\Controllers\\HotelController.php", "source_location": "L93"}, {"caller_nid": "hotelcontroller_hotelcontroller_store", "callee": "auth", "source_file": "C:\\wamp27\\www\\travel_opps\\backend\\app\\Http\\Controllers\\HotelController.php", "source_location": "L93"}, {"caller_nid": "hotelcontroller_hotelcontroller_store", "callee": "createdResponse", "source_file": "C:\\wamp27\\www\\travel_opps\\backend\\app\\Http\\Controllers\\HotelController.php", "source_location": "L96"}, {"caller_nid": "hotelcontroller_hotelcontroller_store", "callee": "refresh", "source_file": "C:\\wamp27\\www\\travel_opps\\backend\\app\\Http\\Controllers\\HotelController.php", "source_location": "L96"}, {"caller_nid": "hotelcontroller_hotelcontroller_store", "callee": "serverErrorResponse", "source_file": "C:\\wamp27\\www\\travel_opps\\backend\\app\\Http\\Controllers\\HotelController.php", "source_location": "L98"}, {"caller_nid": "hotelcontroller_hotelcontroller_update", "callee": "Hotel", "source_file": "C:\\wamp27\\www\\travel_opps\\backend\\app\\Http\\Controllers\\HotelController.php", "source_location": "L108"}, {"caller_nid": "hotelcontroller_hotelcontroller_update", "callee": "notFoundResponse", "source_file": "C:\\wamp27\\www\\travel_opps\\backend\\app\\Http\\Controllers\\HotelController.php", "source_location": "L110"}, {"caller_nid": "hotelcontroller_hotelcontroller_update", "callee": "Validator", "source_file": "C:\\wamp27\\www\\travel_opps\\backend\\app\\Http\\Controllers\\HotelController.php", "source_location": "L112"}, {"caller_nid": "hotelcontroller_hotelcontroller_update", "callee": "all", "source_file": "C:\\wamp27\\www\\travel_opps\\backend\\app\\Http\\Controllers\\HotelController.php", "source_location": "L112"}, {"caller_nid": "hotelcontroller_hotelcontroller_update", "callee": "fails", "source_file": "C:\\wamp27\\www\\travel_opps\\backend\\app\\Http\\Controllers\\HotelController.php", "source_location": "L116"}, {"caller_nid": "hotelcontroller_hotelcontroller_update", "callee": "validationErrorResponse", "source_file": "C:\\wamp27\\www\\travel_opps\\backend\\app\\Http\\Controllers\\HotelController.php", "source_location": "L117"}, {"caller_nid": "hotelcontroller_hotelcontroller_update", "callee": "only", "source_file": "C:\\wamp27\\www\\travel_opps\\backend\\app\\Http\\Controllers\\HotelController.php", "source_location": "L119"}, {"caller_nid": "hotelcontroller_hotelcontroller_update", "callee": "hasFile", "source_file": "C:\\wamp27\\www\\travel_opps\\backend\\app\\Http\\Controllers\\HotelController.php", "source_location": "L132"}, {"caller_nid": "hotelcontroller_hotelcontroller_update", "callee": "file", "source_file": "C:\\wamp27\\www\\travel_opps\\backend\\app\\Http\\Controllers\\HotelController.php", "source_location": "L134"}, {"caller_nid": "hotelcontroller_hotelcontroller_update", "callee": "updatedResponse", "source_file": "C:\\wamp27\\www\\travel_opps\\backend\\app\\Http\\Controllers\\HotelController.php", "source_location": "L141"}, {"caller_nid": "hotelcontroller_hotelcontroller_update", "callee": "refresh", "source_file": "C:\\wamp27\\www\\travel_opps\\backend\\app\\Http\\Controllers\\HotelController.php", "source_location": "L141"}, {"caller_nid": "hotelcontroller_hotelcontroller_update", "callee": "serverErrorResponse", "source_file": "C:\\wamp27\\www\\travel_opps\\backend\\app\\Http\\Controllers\\HotelController.php", "source_location": "L143"}, {"caller_nid": "hotelcontroller_hotelcontroller_destroy", "callee": "Hotel", "source_file": "C:\\wamp27\\www\\travel_opps\\backend\\app\\Http\\Controllers\\HotelController.php", "source_location": "L153"}, {"caller_nid": "hotelcontroller_hotelcontroller_destroy", "callee": "notFoundResponse", "source_file": "C:\\wamp27\\www\\travel_opps\\backend\\app\\Http\\Controllers\\HotelController.php", "source_location": "L155"}, {"caller_nid": "hotelcontroller_hotelcontroller_destroy", "callee": "delete", "source_file": "C:\\wamp27\\www\\travel_opps\\backend\\app\\Http\\Controllers\\HotelController.php", "source_location": "L157"}, {"caller_nid": "hotelcontroller_hotelcontroller_destroy", "callee": "delete", "source_file": "C:\\wamp27\\www\\travel_opps\\backend\\app\\Http\\Controllers\\HotelController.php", "source_location": "L158"}, {"caller_nid": "hotelcontroller_hotelcontroller_destroy", "callee": "deletedResponse", "source_file": "C:\\wamp27\\www\\travel_opps\\backend\\app\\Http\\Controllers\\HotelController.php", "source_location": "L159"}, {"caller_nid": "hotelcontroller_hotelcontroller_destroy", "callee": "serverErrorResponse", "source_file": "C:\\wamp27\\www\\travel_opps\\backend\\app\\Http\\Controllers\\HotelController.php", "source_location": "L161"}, {"caller_nid": "hotelcontroller_hotelcontroller_search", "callee": "input", "source_file": "C:\\wamp27\\www\\travel_opps\\backend\\app\\Http\\Controllers\\HotelController.php", "source_location": "L171"}, {"caller_nid": "hotelcontroller_hotelcontroller_search", "callee": "input", "source_file": "C:\\wamp27\\www\\travel_opps\\backend\\app\\Http\\Controllers\\HotelController.php", "source_location": "L172"}, {"caller_nid": "hotelcontroller_hotelcontroller_search", "callee": "map", "source_file": "C:\\wamp27\\www\\travel_opps\\backend\\app\\Http\\Controllers\\HotelController.php", "source_location": "L174"}, {"caller_nid": "hotelcontroller_hotelcontroller_search", "callee": "get", "source_file": "C:\\wamp27\\www\\travel_opps\\backend\\app\\Http\\Controllers\\HotelController.php", "source_location": "L174"}, {"caller_nid": "hotelcontroller_hotelcontroller_search", "callee": "limit", "source_file": "C:\\wamp27\\www\\travel_opps\\backend\\app\\Http\\Controllers\\HotelController.php", "source_location": "L174"}, {"caller_nid": "hotelcontroller_hotelcontroller_search", "callee": "orWhere", "source_file": "C:\\wamp27\\www\\travel_opps\\backend\\app\\Http\\Controllers\\HotelController.php", "source_location": "L174"}, {"caller_nid": "hotelcontroller_hotelcontroller_search", "callee": "Hotel", "source_file": "C:\\wamp27\\www\\travel_opps\\backend\\app\\Http\\Controllers\\HotelController.php", "source_location": "L174"}, {"caller_nid": "hotelcontroller_hotelcontroller_search", "callee": "successResponse", "source_file": "C:\\wamp27\\www\\travel_opps\\backend\\app\\Http\\Controllers\\HotelController.php", "source_location": "L180"}, {"caller_nid": "hotelcontroller_hotelcontroller_search", "callee": "serverErrorResponse", "source_file": "C:\\wamp27\\www\\travel_opps\\backend\\app\\Http\\Controllers\\HotelController.php", "source_location": "L182"}, {"caller_nid": "hotelcontroller_hotelcontroller_export", "callee": "date", "source_file": "C:\\wamp27\\www\\travel_opps\\backend\\app\\Http\\Controllers\\HotelController.php", "source_location": "L193"}, {"caller_nid": "hotelcontroller_hotelcontroller_export", "callee": "stream", "source_file": "C:\\wamp27\\www\\travel_opps\\backend\\app\\Http\\Controllers\\HotelController.php", "source_location": "L196"}, {"caller_nid": "hotelcontroller_hotelcontroller_export", "callee": "response", "source_file": "C:\\wamp27\\www\\travel_opps\\backend\\app\\Http\\Controllers\\HotelController.php", "source_location": "L196"}, {"caller_nid": "hotelcontroller_hotelcontroller_export", "callee": "fopen", "source_file": "C:\\wamp27\\www\\travel_opps\\backend\\app\\Http\\Controllers\\HotelController.php", "source_location": "L197"}, {"caller_nid": "hotelcontroller_hotelcontroller_export", "callee": "fprintf", "source_file": "C:\\wamp27\\www\\travel_opps\\backend\\app\\Http\\Controllers\\HotelController.php", "source_location": "L198"}, {"caller_nid": "hotelcontroller_hotelcontroller_export", "callee": "chr", "source_file": "C:\\wamp27\\www\\travel_opps\\backend\\app\\Http\\Controllers\\HotelController.php", "source_location": "L198"}, {"caller_nid": "hotelcontroller_hotelcontroller_export", "callee": "chr", "source_file": "C:\\wamp27\\www\\travel_opps\\backend\\app\\Http\\Controllers\\HotelController.php", "source_location": "L198"}, {"caller_nid": "hotelcontroller_hotelcontroller_export", "callee": "chr", "source_file": "C:\\wamp27\\www\\travel_opps\\backend\\app\\Http\\Controllers\\HotelController.php", "source_location": "L198"}, {"caller_nid": "hotelcontroller_hotelcontroller_export", "callee": "fputcsv", "source_file": "C:\\wamp27\\www\\travel_opps\\backend\\app\\Http\\Controllers\\HotelController.php", "source_location": "L199"}, {"caller_nid": "hotelcontroller_hotelcontroller_export", "callee": "Hotel", "source_file": "C:\\wamp27\\www\\travel_opps\\backend\\app\\Http\\Controllers\\HotelController.php", "source_location": "L201"}, {"caller_nid": "hotelcontroller_hotelcontroller_export", "callee": "fputcsv", "source_file": "C:\\wamp27\\www\\travel_opps\\backend\\app\\Http\\Controllers\\HotelController.php", "source_location": "L203"}, {"caller_nid": "hotelcontroller_hotelcontroller_export", "callee": "fclose", "source_file": "C:\\wamp27\\www\\travel_opps\\backend\\app\\Http\\Controllers\\HotelController.php", "source_location": "L206"}]}