{"nodes": [{"id": "c_wamp27_www_travel_opps_backend_app_http_middleware_apierrorhandlermiddleware_php", "label": "ApiErrorHandlerMiddleware.php", "file_type": "code", "source_file": "C:\\wamp27\\www\\travel_opps\\backend\\app\\Http\\Middleware\\ApiErrorHandlerMiddleware.php", "source_location": "L1"}, {"id": "apierrorhandlermiddleware_apierrorhandlermiddleware", "label": "ApiErrorHandlerMiddleware", "file_type": "code", "source_file": "C:\\wamp27\\www\\travel_opps\\backend\\app\\Http\\Middleware\\ApiErrorHandlerMiddleware.php", "source_location": "L10"}, {"id": "apierrorhandlermiddleware_apierrorhandlermiddleware_handle", "label": ".handle()", "file_type": "code", "source_file": "C:\\wamp27\\www\\travel_opps\\backend\\app\\Http\\Middleware\\ApiErrorHandlerMiddleware.php", "source_location": "L15"}, {"id": "apierrorhandlermiddleware_apierrorhandlermiddleware_geterrormessage", "label": ".getErrorMessage()", "file_type": "code", "source_file": "C:\\wamp27\\www\\travel_opps\\backend\\app\\Http\\Middleware\\ApiErrorHandlerMiddleware.php", "source_location": "L58"}, {"id": "apierrorhandlermiddleware_apierrorhandlermiddleware_geterrorcode", "label": ".getErrorCode()", "file_type": "code", "source_file": "C:\\wamp27\\www\\travel_opps\\backend\\app\\Http\\Middleware\\ApiErrorHandlerMiddleware.php", "source_location": "L73"}, {"id": "apierrorhandlermiddleware_apierrorhandlermiddleware_getstatuscode", "label": ".getStatusCode()", "file_type": "code", "source_file": "C:\\wamp27\\www\\travel_opps\\backend\\app\\Http\\Middleware\\ApiErrorHandlerMiddleware.php", "source_location": "L88"}], "edges": [{"source": "c_wamp27_www_travel_opps_backend_app_http_middleware_apierrorhandlermiddleware_php", "target": "closure", "relation": "imports", "confidence": "EXTRACTED", "source_file": "C:\\wamp27\\www\\travel_opps\\backend\\app\\Http\\Middleware\\ApiErrorHandlerMiddleware.php", "source_location": "L5", "weight": 1.0}, {"source": "c_wamp27_www_travel_opps_backend_app_http_middleware_apierrorhandlermiddleware_php", "target": "request", "relation": "imports", "confidence": "EXTRACTED", "source_file": "C:\\wamp27\\www\\travel_opps\\backend\\app\\Http\\Middleware\\ApiErrorHandlerMiddleware.php", "source_location": "L6", "weight": 1.0}, {"source": "c_wamp27_www_travel_opps_backend_app_http_middleware_apierrorhandlermiddleware_php", "target": "log", "relation": "imports", "confidence": "EXTRACTED", "source_file": "C:\\wamp27\\www\\travel_opps\\backend\\app\\Http\\Middleware\\ApiErrorHandlerMiddleware.php", "source_location": "L7", "weight": 1.0}, {"source": "c_wamp27_www_travel_opps_backend_app_http_middleware_apierrorhandlermiddleware_php", "target": "response", "relation": "imports", "confidence": "EXTRACTED", "source_file": "C:\\wamp27\\www\\travel_opps\\backend\\app\\Http\\Middleware\\ApiErrorHandlerMiddleware.php", "source_location": "L8", "weight": 1.0}, {"source": "c_wamp27_www_travel_opps_backend_app_http_middleware_apierrorhandlermiddleware_php", "target": "apierrorhandlermiddleware_apierrorhandlermiddleware", "relation": "contains", "confidence": "EXTRACTED", "source_file": "C:\\wamp27\\www\\travel_opps\\backend\\app\\Http\\Middleware\\ApiErrorHandlerMiddleware.php", "source_location": "L10", "weight": 1.0}, {"source": "apierrorhandlermiddleware_apierrorhandlermiddleware", "target": "apierrorhandlermiddleware_apierrorhandlermiddleware_handle", "relation": "method", "confidence": "EXTRACTED", "source_file": "C:\\wamp27\\www\\travel_opps\\backend\\app\\Http\\Middleware\\ApiErrorHandlerMiddleware.php", "source_location": "L15", "weight": 1.0}, {"source": "apierrorhandlermiddleware_apierrorhandlermiddleware", "target": "apierrorhandlermiddleware_apierrorhandlermiddleware_geterrormessage", "relation": "method", "confidence": "EXTRACTED", "source_file": "C:\\wamp27\\www\\travel_opps\\backend\\app\\Http\\Middleware\\ApiErrorHandlerMiddleware.php", "source_location": "L58", "weight": 1.0}, {"source": "apierrorhandlermiddleware_apierrorhandlermiddleware", "target": "apierrorhandlermiddleware_apierrorhandlermiddleware_geterrorcode", "relation": "method", "confidence": "EXTRACTED", "source_file": "C:\\wamp27\\www\\travel_opps\\backend\\app\\Http\\Middleware\\ApiErrorHandlerMiddleware.php", "source_location": "L73", "weight": 1.0}, {"source": "apierrorhandlermiddleware_apierrorhandlermiddleware", "target": "apierrorhandlermiddleware_apierrorhandlermiddleware_getstatuscode", "relation": "method", "confidence": "EXTRACTED", "source_file": "C:\\wamp27\\www\\travel_opps\\backend\\app\\Http\\Middleware\\ApiErrorHandlerMiddleware.php", "source_location": "L88", "weight": 1.0}, {"source": "apierrorhandlermiddleware_apierrorhandlermiddleware_handle", "target": "apierrorhandlermiddleware_apierrorhandlermiddleware_getstatuscode", "relation": "calls", "confidence": "EXTRACTED", "source_file": "C:\\wamp27\\www\\travel_opps\\backend\\app\\Http\\Middleware\\ApiErrorHandlerMiddleware.php", "source_location": "L24", "weight": 1.0}, {"source": "apierrorhandlermiddleware_apierrorhandlermiddleware_handle", "target": "apierrorhandlermiddleware_apierrorhandlermiddleware_geterrormessage", "relation": "calls", "confidence": "EXTRACTED", "source_file": "C:\\wamp27\\www\\travel_opps\\backend\\app\\Http\\Middleware\\ApiErrorHandlerMiddleware.php", "source_location": "L48", "weight": 1.0}, {"source": "apierrorhandlermiddleware_apierrorhandlermiddleware_handle", "target": "apierrorhandlermiddleware_apierrorhandlermiddleware_geterrorcode", "relation": "calls", "confidence": "EXTRACTED", "source_file": "C:\\wamp27\\www\\travel_opps\\backend\\app\\Http\\Middleware\\ApiErrorHandlerMiddleware.php", "source_location": "L50", "weight": 1.0}], "raw_calls": [{"caller_nid": "apierrorhandlermiddleware_apierrorhandlermiddleware_handle", "callee": "$next", "source_file": "C:\\wamp27\\www\\travel_opps\\backend\\app\\Http\\Middleware\\ApiErrorHandlerMiddleware.php", "source_location": "L18"}, {"caller_nid": "apierrorhandlermiddleware_apierrorhandlermiddleware_handle", "callee": "Log", "source_file": "C:\\wamp27\\www\\travel_opps\\backend\\app\\Http\\Middleware\\ApiErrorHandlerMiddleware.php", "source_location": "L21"}, {"caller_nid": "apierrorhandlermiddleware_apierrorhandlermiddleware_handle", "callee": "method", "source_file": "C:\\wamp27\\www\\travel_opps\\backend\\app\\Http\\Middleware\\ApiErrorHandlerMiddleware.php", "source_location": "L22"}, {"caller_nid": "apierrorhandlermiddleware_apierrorhandlermiddleware_handle", "callee": "fullUrl", "source_file": "C:\\wamp27\\www\\travel_opps\\backend\\app\\Http\\Middleware\\ApiErrorHandlerMiddleware.php", "source_location": "L23"}, {"caller_nid": "apierrorhandlermiddleware_apierrorhandlermiddleware_handle", "callee": "id", "source_file": "C:\\wamp27\\www\\travel_opps\\backend\\app\\Http\\Middleware\\ApiErrorHandlerMiddleware.php", "source_location": "L25"}, {"caller_nid": "apierrorhandlermiddleware_apierrorhandlermiddleware_handle", "callee": "auth", "source_file": "C:\\wamp27\\www\\travel_opps\\backend\\app\\Http\\Middleware\\ApiErrorHandlerMiddleware.php", "source_location": "L25"}, {"caller_nid": "apierrorhandlermiddleware_apierrorhandlermiddleware_handle", "callee": "user", "source_file": "C:\\wamp27\\www\\travel_opps\\backend\\app\\Http\\Middleware\\ApiErrorHandlerMiddleware.php", "source_location": "L26"}, {"caller_nid": "apierrorhandlermiddleware_apierrorhandlermiddleware_handle", "callee": "auth", "source_file": "C:\\wamp27\\www\\travel_opps\\backend\\app\\Http\\Middleware\\ApiErrorHandlerMiddleware.php", "source_location": "L26"}, {"caller_nid": "apierrorhandlermiddleware_apierrorhandlermiddleware_handle", "callee": "Log", "source_file": "C:\\wamp27\\www\\travel_opps\\backend\\app\\Http\\Middleware\\ApiErrorHandlerMiddleware.php", "source_location": "L32"}, {"caller_nid": "apierrorhandlermiddleware_apierrorhandlermiddleware_handle", "callee": "getMessage", "source_file": "C:\\wamp27\\www\\travel_opps\\backend\\app\\Http\\Middleware\\ApiErrorHandlerMiddleware.php", "source_location": "L33"}, {"caller_nid": "apierrorhandlermiddleware_apierrorhandlermiddleware_handle", "callee": "getFile", "source_file": "C:\\wamp27\\www\\travel_opps\\backend\\app\\Http\\Middleware\\ApiErrorHandlerMiddleware.php", "source_location": "L34"}, {"caller_nid": "apierrorhandlermiddleware_apierrorhandlermiddleware_handle", "callee": "getLine", "source_file": "C:\\wamp27\\www\\travel_opps\\backend\\app\\Http\\Middleware\\ApiErrorHandlerMiddleware.php", "source_location": "L35"}, {"caller_nid": "apierrorhandlermiddleware_apierrorhandlermiddleware_handle", "callee": "getTraceAsString", "source_file": "C:\\wamp27\\www\\travel_opps\\backend\\app\\Http\\Middleware\\ApiErrorHandlerMiddleware.php", "source_location": "L36"}, {"caller_nid": "apierrorhandlermiddleware_apierrorhandlermiddleware_handle", "callee": "method", "source_file": "C:\\wamp27\\www\\travel_opps\\backend\\app\\Http\\Middleware\\ApiErrorHandlerMiddleware.php", "source_location": "L38"}, {"caller_nid": "apierrorhandlermiddleware_apierrorhandlermiddleware_handle", "callee": "fullUrl", "source_file": "C:\\wamp27\\www\\travel_opps\\backend\\app\\Http\\Middleware\\ApiErrorHandlerMiddleware.php", "source_location": "L39"}, {"caller_nid": "apierrorhandlermiddleware_apierrorhandlermiddleware_handle", "callee": "id", "source_file": "C:\\wamp27\\www\\travel_opps\\backend\\app\\Http\\Middleware\\ApiErrorHandlerMiddleware.php", "source_location": "L40"}, {"caller_nid": "apierrorhandlermiddleware_apierrorhandlermiddleware_handle", "callee": "auth", "source_file": "C:\\wamp27\\www\\travel_opps\\backend\\app\\Http\\Middleware\\ApiErrorHandlerMiddleware.php", "source_location": "L40"}, {"caller_nid": "apierrorhandlermiddleware_apierrorhandlermiddleware_handle", "callee": "user", "source_file": "C:\\wamp27\\www\\travel_opps\\backend\\app\\Http\\Middleware\\ApiErrorHandlerMiddleware.php", "source_location": "L41"}, {"caller_nid": "apierrorhandlermiddleware_apierrorhandlermiddleware_handle", "callee": "auth", "source_file": "C:\\wamp27\\www\\travel_opps\\backend\\app\\Http\\Middleware\\ApiErrorHandlerMiddleware.php", "source_location": "L41"}, {"caller_nid": "apierrorhandlermiddleware_apierrorhandlermiddleware_handle", "callee": "json", "source_file": "C:\\wamp27\\www\\travel_opps\\backend\\app\\Http\\Middleware\\ApiErrorHandlerMiddleware.php", "source_location": "L46"}, {"caller_nid": "apierrorhandlermiddleware_apierrorhandlermiddleware_handle", "callee": "response", "source_file": "C:\\wamp27\\www\\travel_opps\\backend\\app\\Http\\Middleware\\ApiErrorHandlerMiddleware.php", "source_location": "L46"}, {"caller_nid": "apierrorhandlermiddleware_apierrorhandlermiddleware_handle", "callee": "config", "source_file": "C:\\wamp27\\www\\travel_opps\\backend\\app\\Http\\Middleware\\ApiErrorHandlerMiddleware.php", "source_location": "L49"}, {"caller_nid": "apierrorhandlermiddleware_apierrorhandlermiddleware_handle", "callee": "getMessage", "source_file": "C:\\wamp27\\www\\travel_opps\\backend\\app\\Http\\Middleware\\ApiErrorHandlerMiddleware.php", "source_location": "L49"}]}